codeg/__init__.py
codeg/codeg.py
codeg/codegenerator.py
codeg/consts.py
codeg/exceptions.py
codegenerator/__init__.py
codegenerator/codegenerator.py
codegenerator/consts.py
codeg-0.2.3.dist-info/LICENSE
codeg-0.2.3.dist-info/METADATA
codeg-0.2.3.dist-info/WHEEL
codeg-0.2.3.dist-info/top_level.txt
codeg-0.2.3.dist-info/RECORD
